odoo10_addon_web_fullscreen-10.0.1.0.0.99.dev3-py2.7-nspkg.pth
odoo/addons/web_fullscreen/README.rst
odoo/addons/web_fullscreen/__init__.py
odoo/addons/web_fullscreen/__manifest__.py
odoo/addons/web_fullscreen/i18n/web_fullscreen.pot
odoo/addons/web_fullscreen/static/description/icon.png
odoo/addons/web_fullscreen/static/src/css/web_fullscreen.css
odoo/addons/web_fullscreen/static/src/img/web_fullscreen.gif
odoo/addons/web_fullscreen/static/src/js/web_fullscreen.js
odoo/addons/web_fullscreen/static/src/xml/web_fullscreen_templates.xml
odoo/addons/web_fullscreen/views/web_fullscreen_view.xml
odoo10_addon_web_fullscreen-10.0.1.0.0.99.dev3.dist-info/METADATA
odoo10_addon_web_fullscreen-10.0.1.0.0.99.dev3.dist-info/RECORD
odoo10_addon_web_fullscreen-10.0.1.0.0.99.dev3.dist-info/WHEEL
odoo10_addon_web_fullscreen-10.0.1.0.0.99.dev3.dist-info/namespace_packages.txt
odoo10_addon_web_fullscreen-10.0.1.0.0.99.dev3.dist-info/top_level.txt
